havana/__init__.py
havana/cmc.py
havana-0.0.6.dist-info/LICENCE
havana-0.0.6.dist-info/METADATA
havana-0.0.6.dist-info/WHEEL
havana-0.0.6.dist-info/top_level.txt
havana-0.0.6.dist-info/RECORD
