Metadata-Version: 2.1
Name: havana
Version: 0.0.6
Summary: Python library for Cryptocurrency Markets Analysis and Crypto Algo-Trading
Home-page: 
Author: Pawel Lachowicz
Author-email: enquiries@quantatrisk.com
License: MIT
License-File: LICENCE
Requires-Dist: numpy
Requires-Dist: pandas
Requires-Dist: python-binance (==1.0.17)
Requires-Dist: matplotlib
Requires-Dist: requests
